Workbook

Sheet 说明
B1: 售前毛利测算模板 · 使用说明
B4: 颜色约定(重要)
B5: 蓝色字 | C5: 你要填的输入值 / 可调杠杆。只改蓝色单元格。
B6: 黑色字 | C6: 公式自动计算,请勿手改,改了就断了。
B7: 绿色字 | C7: 从其他工作表引用过来的值。
B8: 黄色底 | C8: 关键假设,务必逐项确认。
B10: 工作表结构
B11: 1. 说明 | C11: 本页。
B12: 2. 假设与输入 | C12: 全局假设:税率、人天成本、折扣、风险预留等。测算的总开关。
B13: 3. 收入明细 | C13: 按行填报价项(软件/硬件/服务/运维),自动算收入合计。
B14: 4. 成本明细 | C14: 对应成本:采购成本、人力投入、差旅、第三方等。
B15: 5. 毛利汇总 | C15: 自动汇总:收入、成本、毛利、毛利率,并做敏感性分析。
B17: 使用步骤
B18: 第 1 步 | C18: 在【假设与输入】填项目基本信息与全局假设。
B19: 第 2 步 | C19: 在【收入明细】逐行填客户报价(含税或不含税见假设页开关)。
B20: 第 3 步 | C20: 在【成本明细】填对应成本;人力按『人天 × 人天成本』自动算。
B21: 第 4 步 | C21: 看【毛利汇总】:毛利率是否达到公司红线,不达标回头调折扣或成本。
B23: 注意
B24: 示例数据 | C24: 各明细表第一行为示例(演示填法),正式使用请覆盖或删除。
B25: 口径 | C25: 默认所有金额为【不含税】口径;如用含税价,请在假设页切换并留意税率处理。
B26: 免责 | C26: 本表为售前内部测算,最终报价以商务/财务审批为准。

Sheet 假设与输入
B1: 假设与输入
B3: 一、项目基本信息
B4: 项目 | C4: 内容 | D4: 说明
B5: 客户名称 | C5: 示例:某某银行 | D5: 填客户全称
B6: 项目名称 | C6: 示例:智能客服平台一期
B7: 测算日期 | C7: 2026-07-26 | D7: 本次测算的日期
B8: 售前负责人
B9: 项目周期(月) | C9: 6 | D9: 用于人力与运维成本估算
B11: 二、全局假设(关键杠杆)
B12: 假设项 | C12: 取值 | D12: 说明
B13: 整体折扣率 | C13: 0 | D13: 对标准报价的整体折让,0% = 不打折
B14: 公司毛利红线 | C14: 0.3 | D14: 低于此毛利率需special申请
B15: 高级工程师人天成本 | C15: 2500 | D15: 内部成本口径(非报价)
B16: 普通工程师人天成本 | C16: 1500 | D16: 内部成本口径
B17: 实施/交付人天成本 | C17: 1800 | D17: 内部成本口径
B18: 差旅单人天成本 | C18: 800 | D18: 含交通住宿餐补
B19: 风险预留比例 | C19: 0.05 | D19: 按总成本计提,应对范围蔓延
B20: 销售费用率 | C20: 0.03 | D20: 按收入计提(渠道/佣金等)
B21: 增值税率 | C21: 0.06 | D21: 仅作参考换算,本表默认不含税口径

Sheet 收入明细
B1: 收入明细(客户报价)
B2: 蓝色为输入;标准报价 = 单价 × 数量;折后收入 = 标准报价 ×(1 − 整体折扣率)
B4: 序号 | C4: 类别 | D4: 项目/产品名称 | E4: 单位 | F4: 数量 | G4: 单价(不含税) | H4: 标准报价 | I4: 折后收入 | J4: 备注
B5: 1 | C5: 软件许可 | D5: 示例:智能客服平台 标准版 License | E5: 套 | F5: 1 | G5: 800000 | H5: =IF(N(F5)*N(G5)=0,0,F5*G5) | I5: =H5*(1-'假设与输入'!$C$13) | J5: 示例行,请覆盖
B6: 2 | H6: =IF(N(F6)*N(G6)=0,0,F6*G6) | I6: =H6*(1-'假设与输入'!$C$13)
B7: 3 | H7: =IF(N(F7)*N(G7)=0,0,F7*G7) | I7: =H7*(1-'假设与输入'!$C$13)
B8: 4 | H8: =IF(N(F8)*N(G8)=0,0,F8*G8) | I8: =H8*(1-'假设与输入'!$C$13)
B9: 5 | H9: =IF(N(F9)*N(G9)=0,0,F9*G9) | I9: =H9*(1-'假设与输入'!$C$13)
B10: 6 | H10: =IF(N(F10)*N(G10)=0,0,F10*G10) | I10: =H10*(1-'假设与输入'!$C$13)
B11: 7 | H11: =IF(N(F11)*N(G11)=0,0,F11*G11) | I11: =H11*(1-'假设与输入'!$C$13)
B12: 8 | H12: =IF(N(F12)*N(G12)=0,0,F12*G12) | I12: =H12*(1-'假设与输入'!$C$13)
B13: 9 | H13: =IF(N(F13)*N(G13)=0,0,F13*G13) | I13: =H13*(1-'假设与输入'!$C$13)
B14: 10 | H14: =IF(N(F14)*N(G14)=0,0,F14*G14) | I14: =H14*(1-'假设与输入'!$C$13)
B15: 11 | H15: =IF(N(F15)*N(G15)=0,0,F15*G15) | I15: =H15*(1-'假设与输入'!$C$13)
B16: 12 | H16: =IF(N(F16)*N(G16)=0,0,F16*G16) | I16: =H16*(1-'假设与输入'!$C$13)
B17: 13 | H17: =IF(N(F17)*N(G17)=0,0,F17*G17) | I17: =H17*(1-'假设与输入'!$C$13)
... B24: 20 | H24: =IF(N(F24)*N(G24)=0,0,F24*G24) | I24: =H24*(1-'假设与输入'!$C$13)
B25: 合计 | H25: =SUM(H5:H24) | I25: =SUM(I5:I24)
B27: 类别参考:软件许可 / 硬件设备 / 实施服务 / 定制开发 / 运维服务 / 第三方产品 / 培训

Sheet 成本明细
B1: 成本明细(内部成本)
B2: 人力成本用【人天】填数量,单位成本从假设页自动带出;其余成本直接填金额
B4: A. 人力成本
B5: 序号 | C5: 角色 | D5: 工作内容 | E5: 人天单价 | F5: 人天数 | G5: 小计 | H5: 备注
B6: 1 | C6: 高级工程师 | D6: 示例:方案设计与架构 | E6: =IF(C6="高级工程师",'假设与输入'!$C$15,IF(C6="普通工程师",'假设与输入'!$C$16,IF(C6="实施/交付",'假设与输入'!$C$17,0))) | F6: 30 | G6: =E6*N(F6) | H6: 示例行,请覆盖
B7: 2 | C7: 普通工程师 | E7: =IF(C7="高级工程师",'假设与输入'!$C$15,IF(C7="普通工程师",'假设与输入'!$C$16,IF(C7="实施/交付",'假设与输入'!$C$17,0))) | G7: =E7*N(F7)
B8: 3 | C8: 实施/交付 | E8: =IF(C8="高级工程师",'假设与输入'!$C$15,IF(C8="普通工程师",'假设与输入'!$C$16,IF(C8="实施/交付",'假设与输入'!$C$17,0))) | G8: =E8*N(F8)
B9: 4 | E9: =IF(C9="高级工程师",'假设与输入'!$C$15,IF(C9="普通工程师",'假设与输入'!$C$16,IF(C9="实施/交付",'假设与输入'!$C$17,0))) | G9: =E9*N(F9)
B10: 5 | E10: =IF(C10="高级工程师",'假设与输入'!$C$15,IF(C10="普通工程师",'假设与输入'!$C$16,IF(C10="实施/交付",'假设与输入'!$C$17,0))) | G10: =E10*N(F10)
B11: 6 | E11: =IF(C11="高级工程师",'假设与输入'!$C$15,IF(C11="普通工程师",'假设与输入'!$C$16,IF(C11="实施/交付",'假设与输入'!$C$17,0))) | G11: =E11*N(F11)
B12: 7 | E12: =IF(C12="高级工程师",'假设与输入'!$C$15,IF(C12="普通工程师",'假设与输入'!$C$16,IF(C12="实施/交付",'假设与输入'!$C$17,0))) | G12: =E12*N(F12)
B13: 8 | E13: =IF(C13="高级工程师",'假设与输入'!$C$15,IF(C13="普通工程师",'假设与输入'!$C$16,IF(C13="实施/交付",'假设与输入'!$C$17,0))) | G13: =E13*N(F13)
B14: 人力成本小计 | G14: =SUM(G6:G13)
B16: B. 其他直接成本
B17: 序号 | C17: 类别 | D17: 说明 | E17: 数量 | F17: 单价 | G17: 小计 | H17: 备注
B18: 1 | C18: 硬件采购 | D18: 示例:GPU 服务器 | E18: 2 | F18: 120000 | G18: =IF(N(E18)*N(F18)=0,0,E18*F18) | H18: 示例行,请覆盖
B19: 2 | C19: 第三方软件/License | G19: =IF(N(E19)*N(F19)=0,0,E19*F19)
B20: 3 | C20: 云资源/带宽 | G20: =IF(N(E20)*N(F20)=0,0,E20*F20)
B21: 4 | C21: 差旅 | D21: 人天数(单人天) | F21: ='假设与输入'!$C$18 | G21: =IF(N(E21)*N(F21)=0,0,E21*F21)
B22: 5 | C22: 培训 | G22: =IF(N(E22)*N(F22)=0,0,E22*F22)
B23: 6 | G23: =IF(N(E23)*N(F23)=0,0,E23*F23)
B24: 7 | G24: =IF(N(E24)*N(F24)=0,0,E24*F24)
B25: 8 | G25: =IF(N(E25)*N(F25)=0,0,E25*F25)
B26: 9 | G26: =IF(N(E26)*N(F26)=0,0,E26*F26)
B27: 10 | G27: =IF(N(E27)*N(F27)=0,0,E27*F27)
B28: 其他成本小计 | G28: =SUM(G18:G27)
B30: C. 成本合计
B31: 人力成本 | C31: =G14
B32: 其他直接成本 | C32: =G28
B33: 直接成本小计 | C33: =C31+C32
B34: 风险预留 | C34: =C33*'假设与输入'!$C$19
B35: 销售费用 | C35: ='收入明细'!$I$25*'假设与输入'!$C$20
B36: 总成本 | C36: =C33+C34+C35

Sheet 毛利汇总
B1: 毛利汇总
B3: 一、核心结果
B4: 指标 | C4: 金额 | D4: 占收入比
B5: 标准报价合计 | C5: ='收入明细'!$H$25
B6: 折后收入(不含税) | C6: ='收入明细'!$I$25
B7: 总成本 | C7: ='成本明细'!$C$36 | D7: =IF(C6=0,0,C7/C6)
B8: 毛利 | C8: =C6-C7 | D8: =IF(C6=0,0,C8/C6)
B9: 毛利率 | C9: =IF(C6=0,0,C8/C6)
B10: 是否达到毛利红线 | C10: =IF(C6=0,"待填数据",IF(C9>='假设与输入'!$C$14,"✅ 达标","⚠️ 低于红线,需申请")) | D10: ="红线 "&TEXT('假设与输入'!$C$14,"0.0%")
B12: 二、敏感性分析:折扣率 → 毛利率
B13: 在当前成本不变的前提下,不同整体折扣率对应的毛利与毛利率
B14: 折扣率 | C14: 折后收入 | D14: 毛利 | E14: 毛利率 | F14: 是否达标
B15: 0 | C15: =$C$5*(1-B15) | D15: =C15-$C$7 | E15: =IF(C15=0,0,D15/C15) | F15: =IF(C15=0,"-",IF(E15>='假设与输入'!$C$14,"✅","⚠️"))
B16: 0.05 | C16: =$C$5*(1-B16) | D16: =C16-$C$7 | E16: =IF(C16=0,0,D16/C16) | F16: =IF(C16=0,"-",IF(E16>='假设与输入'!$C$14,"✅","⚠️"))
B17: 0.1 | C17: =$C$5*(1-B17) | D17: =C17-$C$7 | E17: =IF(C17=0,0,D17/C17) | F17: =IF(C17=0,"-",IF(E17>='假设与输入'!$C$14,"✅","⚠️"))
B18: 0.15 | C18: =$C$5*(1-B18) | D18: =C18-$C$7 | E18: =IF(C18=0,0,D18/C18) | F18: =IF(C18=0,"-",IF(E18>='假设与输入'!$C$14,"✅","⚠️"))
B19: 0.2 | C19: =$C$5*(1-B19) | D19: =C19-$C$7 | E19: =IF(C19=0,0,D19/C19) | F19: =IF(C19=0,"-",IF(E19>='假设与输入'!$C$14,"✅","⚠️"))
B20: 0.25 | C20: =$C$5*(1-B20) | D20: =C20-$C$7 | E20: =IF(C20=0,0,D20/C20) | F20: =IF(C20=0,"-",IF(E20>='假设与输入'!$C$14,"✅","⚠️"))
B21: 0.3 | C21: =$C$5*(1-B21) | D21: =C21-$C$7 | E21: =IF(C21=0,0,D21/C21) | F21: =IF(C21=0,"-",IF(E21>='假设与输入'!$C$14,"✅","⚠️"))
B23: 三、成本结构
B24: 成本项 | C24: 金额 | D24: 占总成本比
B25: 人力成本 | C25: ='成本明细'!$G$14 | D25: =IF($C$7=0,0,C25/$C$7)
B26: 其他直接成本 | C26: ='成本明细'!$G$28 | D26: =IF($C$7=0,0,C26/$C$7)
B27: 风险预留 | C27: ='成本明细'!$C$34 | D27: =IF($C$7=0,0,C27/$C$7)
B28: 销售费用 | C28: ='成本明细'!$C$35 | D28: =IF($C$7=0,0,C28/$C$7)
B30: 说明:本表为售前内部测算,示例数值仅演示公式,正式报价以商务/财务审批为准。
